xtcalc/__init__.py
xtcalc/xtcalc.py
xtcalc-1.2.1.dist-info/METADATA
xtcalc-1.2.1.dist-info/WHEEL
xtcalc-1.2.1.dist-info/top_level.txt
xtcalc-1.2.1.dist-info/RECORD
