Metadata-Version: 2.1
Name: xtcalc
Version: 1.2.1
Summary: Simple calculator
Author: xsvebmx
Author-email: m1rza.ismailov@yandex.ru
